LICENSE
README.md
setup.py
sqliteormmagic/__init__.py
sqliteormmagic/sqliteormmagic.py
sqliteormmagic.egg-info/PKG-INFO
sqliteormmagic.egg-info/SOURCES.txt
sqliteormmagic.egg-info/dependency_links.txt
sqliteormmagic.egg-info/top_level.txt