Metadata-Version: 2.1
Name: sqliteormmagic
Version: 0.0.7
Summary: Facilitates the complex syntax of SQL queries through the use of standard commands for reading / writing to the SQlite3 database in Python program
Home-page: https://github.com/Practic1984/SqliteOrmMagic.git
Author: Practic_old
Author-email: tda.kub@gmail.com
Classifier: Programming Language :: Python :: 3.9
Classifier: License :: OSI Approved :: MIT License
License-File: LICENSE
